{
    "id": "Cristina_Santos_254_20260118_200218",
    "data_salvamento": "2026-01-18 20:02:18",
    "identificacao": {
        "nome_gestante": "Cristina Santos 254",
        "unidade_saude": "Posto de Saúde Jardim Primavera"
    },
    "avaliacao": {
        "inicio_pre_natal_antes_12s": true,
        "consultas_pre_natal": 13,
        "vacinas_completas": "Completa",
        "plano_parto": true,
        "participou_grupos": true,
        "avaliacao_odontologica": true,
        "estratificacao": false,
        "cartao_pre_natal_completo": true
    }
}