{
    "id": "Vanessa_Oliveira_439_20260118_200222",
    "data_salvamento": "2026-01-18 20:02:22",
    "identificacao": {
        "nome_gestante": "Vanessa Oliveira 439",
        "unidade_saude": "Centro de Saúde Bom Pastor"
    },
    "avaliacao": {
        "inicio_pre_natal_antes_12s": true,
        "consultas_pre_natal": 10,
        "vacinas_completas": "Completa",
        "plano_parto": true,
        "participou_grupos": true,
        "avaliacao_odontologica": true,
        "estratificacao": true,
        "cartao_pre_natal_completo": true
    }
}